example_shared_profile.py
example_shared_profile-0.0.1.dist-info/entry_points.txt
example_shared_profile-0.0.1.dist-info/WHEEL
example_shared_profile-0.0.1.dist-info/METADATA
example_shared_profile-0.0.1.dist-info/RECORD
